LexLab/Loop.py
LexLab/Shapes.py
LexLab/__init__.py
LexLab-0.0.7.dist-info/LICENSE
LexLab-0.0.7.dist-info/METADATA
LexLab-0.0.7.dist-info/WHEEL
LexLab-0.0.7.dist-info/top_level.txt
LexLab-0.0.7.dist-info/RECORD
