Metadata-Version: 2.1
Name: LexLab
Version: 0.0.7
Summary: A Python package to simplify game development
Home-page: https://github.com/Robert-DeForrest-Reynolds/LexLab
Author: Robert Lawrence DeForret Reynolds
Author-email: rldr.europa@gmail.com
License: UNKNOWN
Project-URL: Bug Tracker, https://github.com/Robert-DeForrest-Reynolds/LexLab/issues
Platform: UNKNOWN
Classifier: Programming Language :: Python :: 3
Classifier: License :: OSI Approved :: MIT License
Classifier: Operating System :: OS Independent
Requires-Python: >=3.6
License-File: LICENSE
Requires-Dist: pygame
